{ "_id" : { "$oid" : "5110634d2e01f45e7d229f0c" }, "album_name_field" : "", "band_name_field" : "", "created" : "2012-07-09 10:46:02", "description_field" : "", "last_entry" : "", "last_updated" : "2012-07-09 10:46:02", "link_field" : "", "publish_date_field" : "", "site_id" : "74", "site_name" : "CT Indie", "site_url" : "http://www.ctindie.com/feeds/posts/default", "site_weight" : "1", "track_name_field" : "" }
{ "_id" : { "$oid" : "5110634d2e01f45e7d229f0e" }, "site_id" : "70", "site_name" : "A Heart is a Spade", "site_url" : "http://www.aheartisaspade.com/feed/", "site_weight" : "2", "band_name_field" : "title", "album_name_field" : "description", "track_name_field" : "description", "link_field" : "link", "description_field" : "description", "publish_date_field" : null, "last_entry" : null, "created" : "2011-02-23 16:04:02", "last_updated" : "2011-02-23 16:04:03" }
{ "_id" : { "$oid" : "5110634d2e01f45e7d229f0f" }, "site_id" : "69", "site_name" : "Buzzbands LA", "site_url" : "http://buzzbands.la/feed/", "site_weight" : "2", "band_name_field" : "title", "album_name_field" : "description", "track_name_field" : "description", "link_field" : "link", "description_field" : "description", "publish_date_field" : null, "last_entry" : null, "created" : "2011-02-22 18:18:33", "last_updated" : "2011-02-22 18:18:36" }
{ "_id" : { "$oid" : "5110634d2e01f45e7d229f10" }, "album_name_field" : "description", "band_name_field" : "title", "created" : "2011-02-22 18:13:59", "description_field" : "description", "last_entry" : "", "last_updated" : "2011-02-22 18:13:59", "link_field" : "link", "publish_date_field" : "", "site_id" : "68", "site_name" : "NJ Underground", "site_url" : "http://thenjunderground.com/blog/rss.xml", "site_weight" : "2", "track_name_field" : "description" }
{ "_id" : { "$oid" : "5110634d2e01f45e7d229f11" }, "site_id" : "67", "site_name" : "The Bay Bridged", "site_url" : "http://thebaybridged.com/?feed=rss2", "site_weight" : "1", "band_name_field" : "title", "album_name_field" : "description", "track_name_field" : "description", "link_field" : "link", "description_field" : "description", "publish_date_field" : null, "last_entry" : null, "created" : "2011-02-22 18:08:22", "last_updated" : "2011-02-22 18:08:23" }
{ "_id" : { "$oid" : "5110634d2e01f45e7d229f12" }, "site_id" : "65", "site_name" : "Drowned in Sound", "site_url" : "http://drownedinsound.com/feed", "site_weight" : "2", "band_name_field" : "title", "album_name_field" : "atom_content", "track_name_field" : "atom_content", "link_field" : "link", "description_field" : "summary", "publish_date_field" : null, "last_entry" : null, "created" : "2010-11-22 10:01:15", "last_updated" : "2010-11-22 10:01:16" }
{ "_id" : { "$oid" : "5110634d2e01f45e7d229f13" }, "site_id" : "64", "site_name" : "Impose", "site_url" : "http://www.imposemagazine.com/rss/", "site_weight" : "2", "band_name_field" : "title", "album_name_field" : "description", "track_name_field" : "description", "link_field" : "link", "description_field" : "description", "publish_date_field" : null, "last_entry" : null, "created" : "2010-11-19 13:34:49", "last_updated" : "2010-11-19 13:34:52" }
{ "_id" : { "$oid" : "5110634d2e01f45e7d229f14" }, "site_id" : "63", "site_name" : "Yours Truly", "site_url" : "http://yourstru.ly/feed/", "site_weight" : "1", "band_name_field" : "title", "album_name_field" : "description", "track_name_field" : "description", "link_field" : "link", "description_field" : "description", "publish_date_field" : null, "last_entry" : null, "created" : "2010-11-19 09:58:14", "last_updated" : "2010-11-19 09:58:14" }
{ "_id" : { "$oid" : "5110634d2e01f45e7d229f15" }, "site_id" : "59", "site_name" : "Rcrd Lbl", "site_url" : "http://feeds.feedburner.com/rcrdlbl/Main", "site_weight" : "3", "band_name_field" : "title", "album_name_field" : "description", "track_name_field" : "description", "link_field" : "link", "description_field" : "description", "publish_date_field" : null, "last_entry" : null, "created" : "2010-11-10 11:29:12", "last_updated" : "2010-11-10 11:29:12" }
{ "_id" : { "$oid" : "5110634d2e01f45e7d229f16" }, "site_id" : "58", "site_name" : "No Depression", "site_url" : "http://www.nodepression.com/profiles/blog/feed?promoted=1&xn_auth=no", "site_weight" : "3", "band_name_field" : "title", "album_name_field" : "atom_content", "track_name_field" : "atom_content", "link_field" : "link", "description_field" : "atom_content", "publish_date_field" : null, "last_entry" : null, "created" : "2010-11-01 22:53:33", "last_updated" : "2010-11-01 22:53:33" }
{ "_id" : { "$oid" : "5110634d2e01f45e7d229f17" }, "site_id" : "57", "site_name" : "Punk News", "site_url" : "http://punknews.org/feeds/punknews.rdf", "site_weight" : "3", "band_name_field" : "title", "album_name_field" : "description", "track_name_field" : "description", "link_field" : "link", "description_field" : "description", "publish_date_field" : null, "last_entry" : null, "created" : "2010-10-14 11:48:53", "last_updated" : "2010-10-14 11:48:53" }
{ "_id" : { "$oid" : "5110634d2e01f45e7d229f18" }, "site_id" : "55", "site_name" : "The Fader", "site_url" : "http://feeds2.feedburner.com/TheFaderMagazine", "site_weight" : "3", "band_name_field" : "title", "album_name_field" : "description", "track_name_field" : "description", "link_field" : "link", "description_field" : "description", "publish_date_field" : null, "last_entry" : null, "created" : "2010-10-11 09:11:35", "last_updated" : "2010-10-11 09:11:35" }
{ "_id" : { "$oid" : "5110634d2e01f45e7d229f19" }, "site_id" : "52", "site_name" : "Hypem", "site_url" : "http://hypem.com/feed/time/today/1/feed.xml", "site_weight" : "0", "band_name_field" : "title", "album_name_field" : "description", "track_name_field" : "description", "link_field" : "title", "description_field" : "title", "publish_date_field" : null, "last_entry" : null, "created" : "2010-09-16 19:03:11", "last_updated" : "2011-12-14 12:08:12" }
{ "_id" : { "$oid" : "5110634d2e01f45e7d229f1a" }, "album_name_field" : "description", "band_name_field" : "title", "created" : "2010-09-15 09:53:21", "description_field" : "description", "last_entry" : "", "last_updated" : "2010-09-15 09:53:21", "link_field" : "link", "publish_date_field" : "", "site_id" : "51", "site_name" : "Elbows", "site_url" : "http://elbo.ws/posts/feed/", "site_weight" : "1", "track_name_field" : "description" }
{ "_id" : { "$oid" : "5110634d2e01f45e7d229f1b" }, "site_id" : "47", "site_name" : "WFMU", "site_url" : "http://blog.wfmu.org/freeform/rss.xml", "site_weight" : "2", "band_name_field" : "title", "album_name_field" : "description", "track_name_field" : "description", "link_field" : "link", "description_field" : "description", "publish_date_field" : null, "last_entry" : null, "created" : "2010-09-14 21:37:33", "last_updated" : "2010-09-14 21:37:35" }
{ "_id" : { "$oid" : "5110634d2e01f45e7d229f1c" }, "site_id" : "46", "site_name" : "NPR", "site_url" : "http://www.npr.org/rss/rss.php?id=15709577", "site_weight" : "4", "band_name_field" : "title", "album_name_field" : "description", "track_name_field" : "description", "link_field" : "link", "description_field" : "description", "publish_date_field" : null, "last_entry" : null, "created" : "2010-09-14 21:34:52", "last_updated" : "2010-09-14 21:34:52" }
{ "_id" : { "$oid" : "5110634d2e01f45e7d229f1d" }, "site_id" : "45", "site_name" : "Kexp", "site_url" : "http://feeds.kexp.org/KexpBlog", "site_weight" : "3", "band_name_field" : "title", "album_name_field" : "description", "track_name_field" : "description", "link_field" : "link", "description_field" : "description", "publish_date_field" : null, "last_entry" : null, "created" : "2010-09-14 21:32:09", "last_updated" : "2010-09-14 21:32:09" }
{ "_id" : { "$oid" : "5110634d2e01f45e7d229f1e" }, "site_id" : "44", "site_name" : "The Music Slut", "site_url" : "http://feeds.feedburner.com/themusicslut/uTNX", "site_weight" : "1", "band_name_field" : "title", "album_name_field" : "description", "track_name_field" : "description", "link_field" : "link", "description_field" : "title", "publish_date_field" : null, "last_entry" : null, "created" : "2010-09-14 16:07:20", "last_updated" : "2010-09-14 16:07:20" }
{ "_id" : { "$oid" : "5110634d2e01f45e7d229f1f" }, "site_id" : "43", "site_name" : "Gorilla Vs Bear", "site_url" : "http://feeds.feedburner.com/GVSB", "site_weight" : "3", "band_name_field" : "title", "album_name_field" : "content", "track_name_field" : "content", "link_field" : "link", "description_field" : "description", "publish_date_field" : null, "last_entry" : null, "created" : "2010-09-14 16:02:06", "last_updated" : "2010-09-14 16:02:06" }
{ "_id" : { "$oid" : "5110634d2e01f45e7d229f20" }, "site_id" : "42", "site_name" : "Spinner", "site_url" : "http://feeds.feedburner.com/Spinner", "site_weight" : "4", "band_name_field" : "title", "album_name_field" : "description", "track_name_field" : "description", "link_field" : "link", "description_field" : "title", "publish_date_field" : null, "last_entry" : null, "created" : "2010-09-14 15:53:30", "last_updated" : "2010-09-14 15:53:30" }
{ "_id" : { "$oid" : "5110634d2e01f45e7d229f21" }, "site_id" : "40", "site_name" : "The Deli", "site_url" : "http://national.thedelimagazine.com/rss.xml", "site_weight" : "1", "band_name_field" : "title", "album_name_field" : "description", "track_name_field" : "description", "link_field" : "link", "description_field" : "title", "publish_date_field" : null, "last_entry" : null, "created" : "2010-09-07 18:46:02", "last_updated" : "2010-09-07 18:46:02" }
{ "_id" : { "$oid" : "5110634d2e01f45e7d229f22" }, "site_id" : "38", "site_name" : "Prefix Mag", "site_url" : "http://feeds.feedburner.com/prefix?format=xml", "site_weight" : "4", "band_name_field" : "title", "album_name_field" : "description", "track_name_field" : "description", "link_field" : "link", "description_field" : "title", "publish_date_field" : null, "last_entry" : null, "created" : "2010-08-17 23:20:04", "last_updated" : "2010-08-17 23:20:04" }
{ "_id" : { "$oid" : "5110634d2e01f45e7d229f23" }, "site_id" : "36", "site_name" : "Brooklyn Vegan", "site_url" : "http://feeds.feedburner.com/BrooklynVeganFeed?format=xml", "site_weight" : "4", "band_name_field" : "title", "album_name_field" : "description", "track_name_field" : "description", "link_field" : "link", "description_field" : "info", "publish_date_field" : null, "last_entry" : null, "created" : "2010-08-17 23:04:09", "last_updated" : "2010-08-17 23:04:09" }
{ "_id" : { "$oid" : "5110634d2e01f45e7d229f24" }, "site_id" : "35", "site_name" : "Pitchfork Track Reviews", "site_url" : "http://feeds2.feedburner.com/PitchforkTrackReviews", "site_weight" : "3", "band_name_field" : "title", "album_name_field" : "description", "track_name_field" : "description", "link_field" : "link", "description_field" : "title", "publish_date_field" : null, "last_entry" : null, "created" : "2010-08-17 23:01:56", "last_updated" : "2010-08-17 23:01:57" }
{ "_id" : { "$oid" : "5110634d2e01f45e7d229f25" }, "site_id" : "34", "site_name" : "Pitchfork Album Reviews", "site_url" : "http://feeds.feedburner.com/PitchforkAlbumReviews?format=xml", "site_weight" : "4", "band_name_field" : "title", "album_name_field" : "description", "track_name_field" : "description", "link_field" : "link", "description_field" : "title", "publish_date_field" : null, "last_entry" : null, "created" : "2010-08-17 23:01:10", "last_updated" : "2010-08-17 23:01:10" }
{ "_id" : { "$oid" : "5110634d2e01f45e7d229f26" }, "site_id" : "33", "site_name" : "Pitchfork Features", "site_url" : "http://feeds.feedburner.com/PitchforkFeatures?format=xml", "site_weight" : "5", "band_name_field" : "title", "album_name_field" : "description", "track_name_field" : "description", "link_field" : "link", "description_field" : "title", "publish_date_field" : null, "last_entry" : null, "created" : "2010-08-17 23:00:37", "last_updated" : "2010-08-17 23:00:37" }
{ "_id" : { "$oid" : "5110634d2e01f45e7d229f27" }, "site_id" : "32", "site_name" : "Pitchfork News", "site_url" : "http://feeds.feedburner.com/PitchforkLatestNews?format=xml", "site_weight" : "2", "band_name_field" : "title", "album_name_field" : "description", "track_name_field" : "description", "link_field" : "link", "description_field" : "title", "publish_date_field" : null, "last_entry" : null, "created" : "2010-08-17 22:58:44", "last_updated" : "2010-08-17 22:58:44" }
{ "_id" : { "$oid" : "5110634d2e01f45e7d229f28" }, "site_id" : "6", "site_name" : "Stereogum", "site_url" : "http://feeds.feedburner.com/stereogum/cBYa?format=xml", "site_weight" : "4", "band_name_field" : "title", "album_name_field" : "description", "track_name_field" : "description", "link_field" : "link", "description_field" : "title", "publish_date_field" : null, "last_entry" : null, "created" : "2008-05-22 15:50:14", "last_updated" : "2008-05-22 15:50:15" }
